lsst/ts/idl/__init__.py
lsst/ts/idl/utils.py
lsst/ts/idl/version.py
lsst/ts/idl/enums/ATCamera.py
lsst/ts/idl/enums/ATDome.py
lsst/ts/idl/enums/ATHexapod.py
lsst/ts/idl/enums/ATMCS.py
lsst/ts/idl/enums/ATMonochromator.py
lsst/ts/idl/enums/ATPneumatics.py
lsst/ts/idl/enums/ATPtg.py
lsst/ts/idl/enums/ATSpectrograph.py
lsst/ts/idl/enums/ATThermoelectricCooler.py
lsst/ts/idl/enums/ESS.py
lsst/ts/idl/enums/Electrometer.py
lsst/ts/idl/enums/FiberSpectrograph.py
lsst/ts/idl/enums/GIS.py
lsst/ts/idl/enums/Guider.py
lsst/ts/idl/enums/HVAC.py
lsst/ts/idl/enums/LinearStage.py
lsst/ts/idl/enums/MTAOS.py
lsst/ts/idl/enums/MTDome.py
lsst/ts/idl/enums/MTHexapod.py
lsst/ts/idl/enums/MTM1M3.py
lsst/ts/idl/enums/MTM2.py
lsst/ts/idl/enums/MTMount.py
lsst/ts/idl/enums/MTPtg.py
lsst/ts/idl/enums/MTRotator.py
lsst/ts/idl/enums/OCPS.py
lsst/ts/idl/enums/PMD.py
lsst/ts/idl/enums/Scheduler.py
lsst/ts/idl/enums/Script.py
lsst/ts/idl/enums/ScriptQueue.py
lsst/ts/idl/enums/TunableLaser.py
lsst/ts/idl/enums/Watcher.py
lsst/ts/idl/enums/__init__.py
ts_idl-3.7.110000060100.dist-info/METADATA
ts_idl-3.7.110000060100.dist-info/WHEEL
ts_idl-3.7.110000060100.dist-info/top_level.txt
ts_idl-3.7.110000060100.dist-info/RECORD
