Metadata-Version: 2.1
Name: ts-idl
Version: 3.7.110000060100
Summary: Contains helper functions for the generated idl library by ts_sal.
Home-page: UNKNOWN
License: GPL
Platform: UNKNOWN
Provides-Extra: dev
Requires-Dist: documenteer[pipelines] ; extra == 'dev'
